README.md
fetchrss.py
setup.py
fetchrss_api.egg-info/PKG-INFO
fetchrss_api.egg-info/SOURCES.txt
fetchrss_api.egg-info/dependency_links.txt
fetchrss_api.egg-info/requires.txt
fetchrss_api.egg-info/top_level.txt