Metadata-Version: 2.1
Name: fetchrss-api
Version: 0.1.4
Summary: A simple interface for FetchRSS.com API
Home-page: https://github.com/Impacto-jor/fetchrss-api/
Author: Álvaro Justen
Author-email: alvarojusten@gmail.com
License: UNKNOWN
Keywords: api rss facebook instagram
Platform: UNKNOWN
Classifier: Development Status :: 5 - Production/Stable
Classifier: Intended Audience :: Developers
Classifier: License :: OSI Approved :: GNU Lesser General Public License v3 or later (LGPLv3+)
Classifier: Natural Language :: English
Classifier: Operating System :: OS Independent
Classifier: Programming Language :: Python :: 3.7
Classifier: Topic :: Utilities
